rubrical/__init__.py
rubrical/_version.py
rubrical/enum.py
rubrical/main.py
rubrical/rubrical.py
rubrical/comparisons/__init__.py
rubrical/comparisons/semversion.py
rubrical/comparisons/string.py
rubrical/comparisons/utils.py
rubrical/package_managers/__init__.py
rubrical/package_managers/base_package_manager.py
rubrical/package_managers/go.py
rubrical/package_managers/jsonnet.py
rubrical/package_managers/nodejs.py
rubrical/package_managers/python.py
rubrical/package_managers/utilities/git.py
rubrical/reporters/gh.py
rubrical/reporters/terminal.py
rubrical/schemas/__init__.py
rubrical/schemas/configuration.py
rubrical/schemas/package.py
rubrical/schemas/results.py
rubrical/subcommands/__init__.py
rubrical/subcommands/configs.py
rubrical/utilities/console.py
rubrical-2.0.0.dist-info/licenses/LICENSE
rubrical-2.0.0.dist-info/METADATA
rubrical-2.0.0.dist-info/WHEEL
rubrical-2.0.0.dist-info/entry_points.txt
rubrical-2.0.0.dist-info/top_level.txt
rubrical-2.0.0.dist-info/RECORD
