Metadata-Version: 2.4
Name: rubrical
Version: 2.0.0
Summary: A CLI to encourage (😅) people to update their dependencies!
Author-email: Ivan Lee <ivanklee86@gmail.com>
Project-URL: Homepage, https://github.com/ivanklee86/rubrical
Project-URL: Repository, https://github.com/ivanklee86/rubrical
Classifier: Development Status :: 4 - Beta
Classifier: Intended Audience :: Developers
Classifier: Topic :: Software Development :: Build Tools
Requires-Python: >=3.14
License-File: LICENSE
Requires-Dist: typer[standard]>=0.21.1
Requires-Dist: pydantic>=2.0.0
Requires-Dist: semver>=3.0.2
Requires-Dist: pygithub>=2.0.0
Requires-Dist: python-benedict[all]>=0.35.0
Requires-Dist: pyyaml>=6.0
Requires-Dist: requirements-parser>=0.13.0
Requires-Dist: pyproject-parser>=0.14.0
Requires-Dist: setuptools>=80.0.0
Requires-Dist: dom-toml>=2.0.0
Requires-Dist: requirements-detector>=1.3.2
Requires-Dist: toml>=0.10.2
Dynamic: license-file
